castleguard_sdk/__init__.py
castleguard_sdk/anonymizer.py
castleguard_sdk/auth.py
castleguard_sdk/castleguard copy.py
castleguard_sdk/castleguard.py
castleguard_sdk/castleguard_base.py
castleguard_sdk/chat.py
castleguard_sdk/collection.py
castleguard_sdk/embedding.py
castleguard_sdk/heartbeat.py
castleguard_sdk/helpers.py
castleguard_sdk/ner.py
castleguard_sdk/transcription.py
castleguard_sdk/translate.py
castleguard_sdk/vision.py
castleguard_sdk-0.27.dist-info/METADATA
castleguard_sdk-0.27.dist-info/WHEEL
castleguard_sdk-0.27.dist-info/top_level.txt
castleguard_sdk-0.27.dist-info/RECORD
