Metadata-Version: 2.4
Name: castleguard_sdk
Version: 0.27
Summary: A Python SDK for interacting with CastleGuard APIs
Author: Ravi Ramsaran
Author-email: ravi.ramsaran@nextria.ca
Requires-Dist: requests
Requires-Dist: aiohttp
Dynamic: author
Dynamic: author-email
Dynamic: description
Dynamic: description-content-type
Dynamic: requires-dist
Dynamic: summary
